{
  "as_of_date": "2026-06-20",
  "list_type": "ibd50",
  "market": "US",
  "source": "IBD weekly leaders (2026-06-20), confirmed by user",
  "complete": true,
  "expected_count": 30,
  "constituents": [
    {"symbol": "MU", "rank": 1, "company": "Micron Technology"},
    {"symbol": "ALAB", "rank": 2, "company": "Astera Labs"},
    {"symbol": "CRDO", "rank": 3, "company": "Credo Technology"},
    {"symbol": "AGX", "rank": 4, "company": "Argan"},
    {"symbol": "TVTX", "rank": 5, "company": "Travere Therapeutics"},
    {"symbol": "LQDA", "rank": 6, "company": "Liquidia"},
    {"symbol": "SITM", "rank": 7, "company": "SiTime"},
    {"symbol": "HUT", "rank": 8, "company": "Hut 8"},
    {"symbol": "FIX", "rank": 9, "company": "Comfort Systems USA"},
    {"symbol": "AXSM", "rank": 10, "company": "Axsome Therapeutics"},
    {"symbol": "AMD", "rank": 11, "company": "Advanced Micro Devices"},
    {"symbol": "CRS", "rank": 12, "company": "Carpenter Technology"},
    {"symbol": "CECO", "rank": 13, "company": "CECO Environmental"},
    {"symbol": "LRCX", "rank": 14, "company": "Lam Research"},
    {"symbol": "TGTX", "rank": 15, "company": "TG Therapeutics"},
    {"symbol": "BE", "rank": 16, "company": "Bloom Energy"},
    {"symbol": "VRT", "rank": 17, "company": "Vertiv"},
    {"symbol": "INOD", "rank": 18, "company": "Innodata"},
    {"symbol": "OUST", "rank": 19, "company": "Ouster"},
    {"symbol": "COCO", "rank": 20, "company": "Vita Coco"},
    {"symbol": "SEI", "rank": 21, "company": "Solaris Energy Infrastructure"},
    {"symbol": "SNEX", "rank": 22, "company": "StoneX"},
    {"symbol": "TSM", "rank": 23, "company": "Taiwan Semiconductor"},
    {"symbol": "GH", "rank": 24, "company": "Guardant Health"},
    {"symbol": "SKYT", "rank": 25, "company": "SkyWater Technology"},
    {"symbol": "TER", "rank": 26, "company": "Teradyne"},
    {"symbol": "KRYS", "rank": 27, "company": "Krystal Biotech"},
    {"symbol": "OSCR", "rank": 28, "company": "Oscar Health"},
    {"symbol": "DAVE", "rank": 29, "company": "Dave"},
    {"symbol": "SEZL", "rank": 30, "company": "Sezzle"}
  ]
}
